eencijfer/__init__.py
eencijfer/assets/__init__.py
eencijfer/assets/cohorten.py
eencijfer/assets/eencijfer.py
eencijfer/assets/eindexamencijfers.py
eencijfer/assets/transformations/__init__py
eencijfer/assets/transformations/datasets/21RI/croho_naam_opleiding_faculteit.csv
eencijfer/assets/transformations/diploma.py
eencijfer/assets/transformations/local_data.py
eencijfer/assets/transformations/opleiding.py
eencijfer/assets/transformations/postcodes.py
eencijfer/assets/transformations/prestatieafspraken.py
eencijfer/assets/transformations/vooropleiding.py
eencijfer/cli.py
eencijfer/convert/__init__.py
eencijfer/convert/column_converters.py
eencijfer/convert/eencijfer.py
eencijfer/convert/import_definitions/Croho.csv
eencijfer/convert/import_definitions/Croho_vest.csv
eencijfer/convert/import_definitions/Dec_actuele_instelling.csv
eencijfer/convert/import_definitions/Dec_brinnummer.csv
eencijfer/convert/import_definitions/Dec_brinvestigingsnummer.csv
eencijfer/convert/import_definitions/Dec_ho-inst.csv
eencijfer/convert/import_definitions/Dec_ho_ISCED.csv
eencijfer/convert/import_definitions/Dec_isat.csv
eencijfer/convert/import_definitions/Dec_land_naar_herkomstindikking.csv
eencijfer/convert/import_definitions/Dec_landcode.csv
eencijfer/convert/import_definitions/Dec_nationaliteitscode.csv
eencijfer/convert/import_definitions/Dec_postcodecijfers_2023.csv
eencijfer/convert/import_definitions/Dec_postcodecijfers_2024.csv
eencijfer/convert/import_definitions/Dec_vakcode.csv
eencijfer/convert/import_definitions/Dec_vestnr_ho.csv
eencijfer/convert/import_definitions/Dec_vestnr_ho_compleet.csv
eencijfer/convert/import_definitions/Dec_vooropl.csv
eencijfer/convert/import_definitions/Dec_vopl.csv
eencijfer/convert/import_definitions/EV____24.csv
eencijfer/convert/import_definitions/VAKHAVW_____.csv
eencijfer/convert/pii.py
eencijfer/io/__init__.py
eencijfer/io/db.py
eencijfer/io/files.py
eencijfer/settings.py
eencijfer/utils/__init__.py
eencijfer-2024.4.6.dist-info/LICENSE
eencijfer-2024.4.6.dist-info/METADATA
eencijfer-2024.4.6.dist-info/WHEEL
eencijfer-2024.4.6.dist-info/entry_points.txt
eencijfer-2024.4.6.dist-info/RECORD
